sdvclient/__init__.py
sdvclient/api.py
sdvclient/models.py
sdvclient/processing.py
sdvclient/raw.py
sdvclient/utils.py
sdvclient-0.5.1.dist-info/LICENSE
sdvclient-0.5.1.dist-info/WHEEL
sdvclient-0.5.1.dist-info/METADATA
sdvclient-0.5.1.dist-info/RECORD
