Metadata-Version: 2.1
Name: sdvclient
Version: 0.5.1
Summary: Sport Data Valley client library for Python
Home-page: https://info.sportdatavalley.nl
License: MIT
Author: Aart Goossens
Author-email: aart@sportdatavalley.nl
Requires-Python: >=3.6.1,<4.0.0
Classifier: License :: OSI Approved :: MIT License
Classifier: Programming Language :: Python :: 3
Classifier: Programming Language :: Python :: 3.7
Classifier: Programming Language :: Python :: 3.8
Classifier: Programming Language :: Python :: 3.9
Requires-Dist: pandas (>=1.0.5,<2.0.0)
Requires-Dist: pydantic (>=1.5.1,<2.0.0)
Requires-Dist: requests (>=2.24.0,<3.0.0)
Project-URL: Documentation, https://gitlab.com/sportdatavalley/sdvclient-python
Project-URL: Repository, https://gitlab.com/sportdatavalley/sdvclient-python
